chikoo/__init__.py
chikoo/cli.py
chikoo/core.py
chikoo-0.1.1.dist-info/METADATA
chikoo-0.1.1.dist-info/WHEEL
chikoo-0.1.1.dist-info/entry_points.txt
chikoo-0.1.1.dist-info/top_level.txt
chikoo-0.1.1.dist-info/RECORD
