Metadata-Version: 2.2
Name: chikoo
Version: 0.1.1
Summary: Experimental computing CLI utility
Author-email: bhishe <example@gmail.com>
